hub/__init__.py
hub-3.0.1.dist-info/METADATA
hub-3.0.1.dist-info/WHEEL
hub-3.0.1.dist-info/top_level.txt
hub-3.0.1.dist-info/RECORD
